cleansetext/__init__.py
cleansetext/pipeline.py
cleansetext/pipeline_test.py
cleansetext/steps.py
cleansetext/steps_test.py
cleansetext-1.1.0.dist-info/LICENSE
cleansetext-1.1.0.dist-info/METADATA
cleansetext-1.1.0.dist-info/WHEEL
cleansetext-1.1.0.dist-info/top_level.txt
cleansetext-1.1.0.dist-info/RECORD
